pandas_profiling/__init__.py
pandas_profiling/compare_reports.py
pandas_profiling/config.py
pandas_profiling/config_default.yaml
pandas_profiling/config_minimal.yaml
pandas_profiling/expectations_report.py
pandas_profiling/profile_report.py
pandas_profiling/serialize_report.py
pandas_profiling/version.py
pandas_profiling/controller/__init__.py
pandas_profiling/controller/console.py
pandas_profiling/controller/pandas_decorator.py
pandas_profiling/model/__init__.py
pandas_profiling/model/alerts.py
pandas_profiling/model/correlations.py
pandas_profiling/model/dataframe.py
pandas_profiling/model/describe.py
pandas_profiling/model/duplicates.py
pandas_profiling/model/expectation_algorithms.py
pandas_profiling/model/handler.py
pandas_profiling/model/missing.py
pandas_profiling/model/pairwise.py
pandas_profiling/model/sample.py
pandas_profiling/model/summarizer.py
pandas_profiling/model/summary.py
pandas_profiling/model/summary_algorithms.py
pandas_profiling/model/table.py
pandas_profiling/model/typeset.py
pandas_profiling/model/typeset_relations.py
pandas_profiling/model/pandas/__init__.py
pandas_profiling/model/pandas/correlations_pandas.py
pandas_profiling/model/pandas/dataframe_pandas.py
pandas_profiling/model/pandas/describe_boolean_pandas.py
pandas_profiling/model/pandas/describe_categorical_pandas.py
pandas_profiling/model/pandas/describe_counts_pandas.py
pandas_profiling/model/pandas/describe_date_pandas.py
pandas_profiling/model/pandas/describe_file_pandas.py
pandas_profiling/model/pandas/describe_generic_pandas.py
pandas_profiling/model/pandas/describe_image_pandas.py
pandas_profiling/model/pandas/describe_numeric_pandas.py
pandas_profiling/model/pandas/describe_path_pandas.py
pandas_profiling/model/pandas/describe_supported_pandas.py
pandas_profiling/model/pandas/describe_timeseries_pandas.py
pandas_profiling/model/pandas/describe_url_pandas.py
pandas_profiling/model/pandas/discretize_pandas.py
pandas_profiling/model/pandas/duplicates_pandas.py
pandas_profiling-3.6.6.dist-info/LICENSE
pandas_profiling-3.6.6.dist-info/METADATA
pandas_profiling-3.6.6.dist-info/WHEEL
pandas_profiling-3.6.6.dist-info/entry_points.txt
pandas_profiling-3.6.6.dist-info/top_level.txt
pandas_profiling-3.6.6.dist-info/RECORD
