Metadata-Version: 2.1
Name: pandas-profiling
Version: 3.6.6
Summary: Deprecated 'pandas-profiling' package, use 'ydata-profiling' instead
Home-page: https://github.com/ydataai/pandas-profiling
Author: YData Labs Inc
Author-email: opensource@ydata.ai
License: MIT
Keywords: pandas data-science data-analysis python jupyter ipython
Platform: UNKNOWN
Classifier: Development Status :: 5 - Production/Stable
Classifier: Topic :: Software Development :: Build Tools
Classifier: License :: OSI Approved :: MIT License
Classifier: Environment :: Console
Classifier: Operating System :: OS Independent
Classifier: Intended Audience :: Science/Research
Classifier: Intended Audience :: Developers
Classifier: Intended Audience :: Financial and Insurance Industry
Classifier: Intended Audience :: Healthcare Industry
Classifier: Topic :: Scientific/Engineering
Classifier: Framework :: IPython
Classifier: Programming Language :: Python :: 3
Requires-Python: >=3.7, <3.11
Provides-Extra: notebook
Provides-Extra: unicode
